bpprosdk/__init__.py
bpprosdk/tests/__init__.py
bpprosdk/tests/test_account_history_channel.py
bpprosdk/tests/test_orderbook_channel.py
bpprosdk/tests/test_orderbook_store.py
bpprosdk/tests/test_orders_channel.py
bpprosdk/tests/test_trading_channel.py
bpprosdk/tests/test_wss_connection.py
bpprosdk/websockets/__init__.py
bpprosdk/websockets/subscriptions.py
bpprosdk/websockets/unsubscription.py
bpprosdk/websockets/websocket_client.py
bpprosdk/websockets/websocket_client_advanced.py
bpprosdk/websockets/account/__init__.py
bpprosdk/websockets/account/account_state.py
bpprosdk/websockets/orderbook/__init__.py
bpprosdk/websockets/orderbook/orderbook.py
bpprosdk/websockets/orders/__init__.py
bpprosdk/websockets/orders/cancel_order.py
bpprosdk/websockets/orders/create_order.py
bpprosdk/websockets/orders/events.py
bpprosdk/websockets/orders/orders_message_handler.py
bpprosdk/websockets/trading/__init__.py
bpprosdk/websockets/trading/account_history_channel_payloads.py
bpprosdk/websockets/trading/account_history_message_handler.py
bpprosdk/websockets/trading/trading_channel_events.py
bpprosdk/websockets/trading/trading_message_handler.py
bitpanda_pro_sdk-0.7.2.dist-info/LICENSE
bitpanda_pro_sdk-0.7.2.dist-info/METADATA
bitpanda_pro_sdk-0.7.2.dist-info/WHEEL
bitpanda_pro_sdk-0.7.2.dist-info/top_level.txt
bitpanda_pro_sdk-0.7.2.dist-info/RECORD
